[
    {
        "message": "ブリッジなら貴賓室を出てすぐそこだ。しかし心理的な距離は遠い。"
    },
    {
        "name": "恭介",
        "message": "「・・・・・・」"
    },
    {
        "name": "恭介",
        "message": "「やっぱりこうなるのか」"
    },
    {
        "name": "恵",
        "message": "「まあ、全員で入る必要はないわけだし」"
    },
    {
        "name": "明乃",
        "message": "「恭ちゃ〜〜〜ん、がんばれぇ〜〜〜」"
    },
    {
        "name": "恭介",
        "message": "「おうよ、まかせとけ」"
    },
    {
        "message": "身勝手にふむふむと納得している恵と、間延びした声援を送る明乃、遠くから見守るだけの二人に俺は肩越しに手をあげて答える。"
    },
    {
        "message": "惨劇が行われてからどれだけ経つのか正確な時間はわからないが、異様な臭気がブリッジを包み始めていた。"
    },
    {
        "message": "卵が腐った・・・いわゆる硫黄のような臭いだ。長く吸っているとこの場で行き倒れになりそうだった。"
    },
    {
        "message": "俺は足元の赤色や白、それらが混じった桃色をできるだけ見ないようにして足を進めていく。"
    },
    {
        "message": "船長の亡骸は以前と同じ姿のまま横たわっていた。"
    },
    {
        "name": "恭介",
        "message": "（勝手ですが、お借りします）"
    },
    {
        "message": "硬直した首の後ろへと手を回す。温もりを失った人の肌はまるで厚手のゴムで出来た作り物のような感触がした。"
    },
    {
        "message": "ペンダントがどうしても外れない。だが、遺体を動かす気にはなれず、不作法ではあるが鎖を引きちぎり早足にブリッジを後にする。"
    },
    {
        "message": "誰かが生唾を呑み込む。だがこの場にいる誰もがその音に注意を払わなかった。"
    },
    {
        "message": "鍵の形状は、一見してケースの鍵穴と一致しているように思える。俺は錆ひとつない銀白色の鍵を、ピンセットで細い穴を探るように構えた。"
    },
    {
        "message": "奥まで押し込み、回す。"
    },
    {
        "message": "鍵が止まる。引っかかりはわずかに力を加えただけですぐに消えた。"
    },
    {
        "name": "明乃",
        "message": "「お、お、お・・・」"
    },
    {
        "name": "恵",
        "message": "「・・・・・・」"
    },
    {
        "message": "黒光りする金属の固まり。ケースの中の型どりされた窪みには、オートマチックの拳銃が無言で収まっていた。"
    },
    {
        "message": "生唾を呑み込む音。今度は俺のものだった。指紋の跡ひとつない表面に触れる。人肌を拒絶するように冷えた感触。"
    },
    {
        "message": "持ち上げると、重みでわずかに手が下がった。艶を入れられたプラスチック製ではない。間違いなく本物だった。"
    },
    {
        "message": "人を殺すための道具。"
    },
    {
        "message": "一人を殺すことに特化した武器。"
    },
    {
        "message": "こいつの銃口が向く先、人の命は引き金の軽さと等しくなる。"
    },
    {
        "name": "恵",
        "message": "「何発撃てるの？」"
    },
    {
        "message": "恵の言葉に、ただ固唾をのむばかりだった俺と明乃は顔を見合わせた。"
    },
    {
        "message": "ロックを外して弾倉を滑らせる。銃弾を押し上げるバネ仕掛けの底部は一番上までスライドされていた。"
    },
    {
        "message": "つまり弾は入っていない。遊底を引いてみるが薬室内も空だった。"
    },
    {
        "name": "恭介",
        "message": "「は・・・はっ」"
    },
    {
        "message": "急に力が抜けてくる。今までの苦労と緊張は何だったんだ。弾がなければ拳銃など出来の悪い殴打の武器でしかなくなる。"
    },
    {
        "name": "明乃",
        "message": "「ど、どうして・・・！」"
    },
    {
        "name": "恵",
        "message": "「ケースには？」"
    },
    {
        "name": "恭介",
        "message": "「ないな・・・」"
    },
    {
        "message": "ケース内には拳銃本体とは別にちょうど弾倉二本分の窪みはあるが、今は何も収められていない。"
    },
    {
        "message": "何てことだ。殺傷力を発生させる肝心の部分がないなんて。"
    },
    {
        "message": "一発でも撃てれば船内のパワーバランスは大きく変わる。奴もおいそれと俺たちに手が出せなくなる。"
    },
    {
        "message": "ありふれた銃弾ひとつが見つかるかどうかで、この船にいる全ての者の運命が左右されるというのに。"
    },
    {
        "name": "明乃",
        "message": "「何か、弾の代わりになるようなものはないの・・・？」"
    },
    {
        "name": "恭介",
        "message": "「そんなのあるかよ」"
    },
    {
        "name": "恵",
        "message": "「そのものを見つけないことにはね」"
    },
    {
        "message": "拳銃は貴賓室の隠し金庫の中。ガンケースの鍵は船長のペンダント。"
    },
    {
        "message": "ということは、弾もこの二人のどちらかが所有していたと見るべきなのか。"
    },
    {
        "message": "だが貴賓室はあらかた調べた後だし、船長室には入れない。捜索の範囲を広げるにしても、何の手がかりもなく探すにはこの船は広く人手は足りない。"
    },
    {
        "message": "拳銃を手に入れるまでだって偶然の連続だった。同じ幸運をもう一度期待するのは無理というものだ。"
    },
    {
        "message": "気は急くがどうすればいいのかわからない。俺は意味もなく遊底を引いては戻す。"
    },
    {
        "message": "スライドは滑らかで、いざという時のためにちゃんと手入れをされていることがわかった。"
    },
    {
        "message": "使用を想定しているなら、弾もそう難しい場所にはないと思うのだが・・・"
    },
    {
        "name": "恵",
        "message": "「むしろ見つかるなら弾の方がよかったわね」"
    },
    {
        "name": "明乃",
        "message": "「え・・・どうして？」"
    },
    {
        "name": "恵",
        "message": "「火薬は弾の方に入ってるのよ」"
    },
    {
        "message": "わかりきったことだが明乃にしてみれば自分の苦労を否定されたようで、微妙に傷ついたように黙り込む。"
    },
    {
        "name": "恭介",
        "message": "「その弾だって拳銃がなければ役には立たないさ」"
    },
    {
        "name": "恵",
        "message": "「そうかしら」"
    },
    {
        "message": "恵のやつ、さっきから妙な具合に明乃に突っかかってくるな。"
    },
    {
        "message": "俺の知る限り二人は親友だったはずなんだが、この異常な事態の中にあってわずかなほころびが拡大されているのだろうか。"
    },
    {
        "message": "それより今は弾丸のことだ。"
    },
    {
        "message": "拳銃の入ったケースは航行責任者である志乃さんが。その鍵は船長が所有していた。"
    },
    {
        "message": "だとすれば、弾丸は誰が持っている？"
    },
    {
        "message": "明乃・・・？"
    },
    {
        "message": "後回しにする"
    }
]