[
    {
        "name": "可憐",
        "message": "「ちょ、ちょっとどこ触ってんのよ！」"
    },
    {
        "message": "背中に手を回しただけなんだが。"
    },
    {
        "name": "恭介",
        "message": "「少し静かにしてろ」"
    },
    {
        "name": "可憐",
        "message": "「な、なに急にすかしてるのよ。私がうろたえてるとでも言いたいわけ？　警戒心ばかり強い自意識過剰とでも？」"
    },
    {
        "name": "可憐",
        "message": "「はん、どうってことないわよ、この程度。それとは話が別よ。そもそも私があんたの言いなりになる理由なんてこれっぽっちもないんだから」"
    },
    {
        "name": "可憐",
        "message": "「だいたいそんな言い方は卑怯だわ！　自分に都合のいいよう常識をねじ曲げて！」"
    },
    {
        "name": "可憐",
        "message": "「なによ、黙り込んで。その目はなに」"
    },
    {
        "name": "可憐",
        "message": "「あーそう。そうなの。どうあっても私がみっともないってことにしたいわけね」"
    },
    {
        "name": "可憐",
        "message": "「いいわ、だったらキスくらいめぐんでやっても。したいなら勝手に・・・むぐぅ！？」"
    },
    {
        "message": "流れがよくわからないが、可憐が目を閉じた隙に、俺は素早く可憐の口を押さえた。半ば抱え上げるようにして、浴室内に連れ込む。"
    },
    {
        "name": "可憐",
        "message": "「ちょ、ちょ、ちょっと！？　なになになに！？　こら恭介！！」"
    },
    {
        "message": "浴室内を見渡すが、ろくに隠れる場所はない。浴槽の陰くらいか。俺は可憐を抱えたまま奥へ向かう。"
    },
    {
        "name": "可憐",
        "message": "「バカバカバカぁ〜！！　この、とーへんぼく！！　ものには順序ってものがぁぁあああ〜〜〜」"
    },
    {
        "message": "暴れる可憐の体をくるりと回し、横倒しにしてうつぶせに床へ降ろす。"
    },
    {
        "name": "可憐",
        "message": "「ひゃあぁぁぁああ！？」"
    },
    {
        "message": "浴槽から溢れたお湯が下着に染み通り、可憐は頭のてっぺんから声を上げた。"
    },
    {
        "message": "思わず身を起こそうとする可憐を、俺は覆いかぶさるようにして再び床に押しつける。"
    },
    {
        "message": "ゴチン。"
    },
    {
        "message": "可憐は頭から床にぶつかり、ボーリング玉を落としたような音がする。俺は咄嗟に可憐の口を手でふさぎ、呻き声を押し込めた。"
    },
    {
        "name": "可憐",
        "message": "「ぐぬぬぅ・・・」"
    },
    {
        "message": "可憐は目に涙を浮かべて恨めしそうに俺を睨んでくる。"
    },
    {
        "message": "だが、俺の気配から状況が尋常でないことをようやく察したのか、おとなしく湿ったタイルの上に身を伏せている。"
    },
    {
        "message": "もう喚きだす心配はないだろう。俺は可憐の口から手のひらを離す。"
    },
    {
        "name": "可憐",
        "message": "（着替えたばかりなのに・・・）"
    },
    {
        "message": "さっそく漏れてきた呟き声を、俺は唇に指を立てて黙らせる。"
    },
    {
        "message": "どれほど息を潜めていただろうか。"
    },
    {
        "message": "可憐がそわそわと落ち着きを失い始めた頃、大浴場のガラス戸が開かれた。可憐はすぐに身動きをやめる。"
    },
    {
        "message": "可憐を押さえている腕に思わず力がこもる。俺の緊張が伝わったのか、可憐はうつ伏せのままごくりと喉を鳴らした。"
    },
    {
        "message": "足音は・・・近づいてこない。"
    },
    {
        "message": "俺たちに気づいていないのか。それとも入ってきたのは岸田ではないのか。"
    },
    {
        "message": "相手を確かめたくなるが、今はまだ浴槽の陰から顔を出すわけには行かない。"
    },
    {
        "message": "俺たちは立ち上る湿気の中でうずくまる。ひたすら耳を澄ませて。"
    },
    {
        "name": "岸田",
        "message": "「着替えが残っていたよ」"
    },
    {
        "message": "背筋が凍りつく。浴室は湯気で満ちているというのに、肌を伝う汗は冷え切っていた。可憐の顔色がみるみる青ざめていく。"
    },
    {
        "message": "俺たちがここにいることはバレている。しかも、浴室内には他に隠れる場所などない。俺たちが浴槽の陰にいることは、奴にも知られている。"
    },
    {
        "message": "布地を縦に引き裂くような音が聞こえてきた。ゆっくりと、ことさらゆっくり、俺たちの神経をいたぶるように。"
    },
    {
        "message": "あれほど気丈な可憐が、小動物のように肩を震わせている。自分の着替えを裂かれるというのは、ある意味、自分の身の一部を傷つけられることにも似ていた。"
    },
    {
        "message": "突然、暴力的なサイレンが辺りに響き渡る。"
    },
    {
        "message": "咄嗟に両耳を手で塞ぐが、殴りつけるような音の洪水の前には何の役にも立たない。"
    },
    {
        "message": "奇妙な共鳴は、船体が震えているせいなのか。音響そのものが物理的な形を持っているかのようだ。"
    },
    {
        "name": "？？？",
        "message": "『犯人に告ぐ！！』"
    },
    {
        "message": "拡声器で最大限に強化された音声が俺たちの耳朶を叩く。鼓膜が割れそうに痛んだ。可憐は耳を押さえて瞼まできつく閉じている。"
    },
    {
        "name": "？？？",
        "message": "『周囲は完全に包囲した！！　もう逃げられない！！』"
    },
    {
        "name": "？？？",
        "message": "『人質を解放し、武器を捨てて出てきなさい！！』"
    },
    {
        "name": "岸田",
        "message": "「ばかな・・・」"
    },
    {
        "message": "こればかりは俺も岸田と同じ感想を持った。ありえることではなかった。陸を遙かに離れた公海上で、こうも早く警察組織が駆けつけるなど。"
    },
    {
        "message": "しかも、呼びかけている声は日本語だ。そもそもどうやってこの船の事態を知りえたんだ？？？"
    },
    {
        "name": "？？？",
        "message": "『これ以上抵抗しても無駄に罪を重ねるだけだぞ！！』"
    },
    {
        "message": "鋭い舌打ち。足音が遠ざかっていく。奴にしてみれば、俺たちに関わっている状況ではない。"
    },
    {
        "message": "しばらく間を置いてから、俺は戸惑いながらも顔を上げた。"
    },
    {
        "message": "出入り口の辺りに切り裂かれた布地、おそらく可憐の着替えが散乱している。浴室内に岸田の姿はない。"
    },
    {
        "message": "窓から外の様子を窺うが、窓の位置が高いので視界が狭い。見渡す範囲では他の船舶はなかった。"
    },
    {
        "message": "海上保安庁なのか自衛隊なのかは知らないが、駆けつけた船はこちらの右舷に横づけしているようだ。"
    },
    {
        "name": "恭介",
        "message": "（しかし、さっきの呼びかけはどこかで聞いたような気が・・・）"
    },
    {
        "message": "船内にいる者の声ではなかったが、どうも聞き覚えがある。"
    },
    {
        "message": "いや、今は考え込んでいる場合じゃない。"
    },
    {
        "message": "助けが来たからといって俺たちの安全が確定したわけではない。多少不審はあるが、今は行動するべきだ。"
    },
    {
        "message": "俺は可憐の腕を引き上げて立たせる。俺のリードに、可憐は普段とはまるで違った従順さで従う。"
    },
    {
        "message": "可憐の体は浴槽から溢れた湯に濡れ、下着の内側には膨らみが張りついていたが、それを騒ぐ余裕もなかった。"
    },
    {
        "message": "浴室から脱衣所へ。さらに廊下を覗く。"
    },
    {
        "message": "岸田の姿は見あたらない。即座に俺は廊下へ飛び出した。"
    },
    {
        "name": "恭介",
        "message": "「っっっ！？」"
    },
    {
        "message": "調理室から出てきた岸田といきなり出くわす。"
    },
    {
        "message": "奴も大浴場の窓からは船影を見つけることができず、反対側を確認しに行ったようだ。"
    },
    {
        "message": "俺は大浴場。奴は調理室。距離はある。まだ逃げられる。"
    },
    {
        "message": "だが、俺の足はその場に釘づけとなった。"
    },
    {
        "message": "明乃・・・志乃さん・・・。"
    },
    {
        "message": "岸田の背後、調理室の中には二人らしき人影があった。"
    },
    {
        "message": "外部からの介入に対して、取りあえず人質にしようと手元に引き寄せたのだろう。"
    },
    {
        "message": "岸田が俺を見つけてニヤリと笑う。"
    },
    {
        "message": "口元では笑っているが、不測の事態に眼差しには迷いの色がちらついている。"
    },
    {
        "message": "岸田の影がこちらに傾く。"
    },
    {
        "message": "鳴り響く重低音。岸田の鬼相が迫り来る。"
    },
    {
        "message": "立ちつくす間にもはや逃げる余裕すらなくなっていた。"
    },
    {
        "name": "恭介",
        "message": "「くそっ・・・！！」"
    },
    {
        "message": "俺は二人を見捨てて隔壁を閉じた。すぐさま舵輪のようなホイールハンドルを回す。"
    },
    {
        "message": "ハンドルは隔壁の両側についているが、ロックはこちらにしかない。完全に閉めれば向こう側からは開くことができなくなる。"
    },
    {
        "name": "恭介",
        "message": "「っっ！？」"
    },
    {
        "message": "あと半周というところで急にハンドルが動かなくなった。"
    },
    {
        "name": "恭介",
        "message": "「くっ、くくっ・・・！」"
    },
    {
        "message": "むしろ、逆に回り始める。体ごとハンドルの下に潜り込むが、それでもじりじりと巻き返されて膝が床につく。"
    },
    {
        "name": "恭介",
        "message": "「可憐、手伝え、早く・・・！」"
    },
    {
        "message": "大浴場の出口で呆然としていた可憐は、自分の名前を呼ばれてようやくハッと我に返る。"
    },
    {
        "message": "慌ててホイールハンドルの反対側にとりつき、突き出た握りに全体重をかける。"
    },
    {
        "name": "恭介",
        "message": "「ぐぐ・・・何やって・・・もっと力こめろ・・・！」"
    },
    {
        "name": "可憐",
        "message": "「これ以上、無理よ！　もう足が浮いてる！」"
    },
    {
        "message": "可憐の側では、押し上げるのではなく引き下げる以上、込められる力は自重が限界となる。"
    },
    {
        "name": "可憐",
        "message": "「軽いんだからこれで精いっぱい！」"
    },
    {
        "name": "恭介",
        "message": "「わ、笑わすなよ」"
    },
    {
        "name": "可憐",
        "message": "「笑わせてなんかないわよっ！」"
    },
    {
        "message": "二人がかりでようやくハンドルの均衡が保たれる。だが、それではいつまで経っても隔壁をロックできない。"
    },
    {
        "message": "こうなったら、押し返すのはあきらめてこの状態で固定することを考えるべきか。"
    }
]