[
    {
        "message": "いない。"
    },
    {
        "message": "思い切って身を乗り出し、辺りを広く見回す。この時間に客が一人もいないラウンジというのは妙なものだ。"
    },
    {
        "message": "注意深く歩を進める。カウンターの中を覗き込む時には多少の勇気を要したが、そこにも人の姿はなかった。"
    },
    {
        "name": "女のコ",
        "message": "「・・・っ・・・」"
    },
    {
        "message": "隣からかすかに声が聞こえた。耳を澄ますと、それが女のコの押し殺された呻き声であることがわかった。"
    },
    {
        "message": "・・・やはりグリルか。"
    },
    {
        "message": "果たして、岸田もそこにいるのか。"
    },
    {
        "message": "そろそろ恵が回り込んでくる頃だろう。その前に奴の位置を掴んでおきたい。俺は身を低くして壁に沿い、首を伸ばしてグリルを覗き込む。"
    },
    {
        "message": "明乃は手枷首枷を畳まれたまま、床に転がされている。さらに足を縛られ、目隠しに猿ぐつわまで足されて、ほとんど物扱いだ。"
    },
    {
        "message": "グリル内でも、船尾ロビーへの通路の近くに奴はいた。俺のいるラウンジとは反対側で、奴はちょうど俺に背を向ける形になっている。"
    },
    {
        "message": "奴の手元からは金属が軽くぶつかるような音が聞こえていた。スプーンやフォークなどの食器を吟味しているらしい。"
    },
    {
        "message": "明乃を荷物のように転がしておいて、なぜ食器を選んでいるのか理由はわからないが、食事のためではありえない。"
    },
    {
        "message": "岸田と明乃の二人をおいては、人影は見当たらない。そう思った瞬間、船尾ロビーの方から拳銃を握りしめた恵が現れる。"
    },
    {
        "message": "まずい。恵は十分に周囲を警戒しているようだが、このままグリルに出れば岸田と遭遇する時の距離が近すぎる。"
    },
    {
        "message": "かといって、俺からではクロスボウで奴を狙撃するには遠すぎる。別方向から同時に攻撃するため二手に分かれたことが完全に裏目に出た。"
    },
    {
        "message": "どうするか。岸田は相変わらず手元でカチャカチャと音を立てているが、恵がそれに気づく様子はない。"
    },
    {
        "message": "冷や汗が背中を伝い落ちる。仕方ない、恵と岸田が鉢合わせする寸前に、無理を承知で俺が狙撃するまでだ。"
    },
    {
        "message": "恵がすぐさま岸田に銃を向けてくれることを祈るしかない。俺はクロスボウを視線の高さに構えた。"
    },
    {
        "message": "恵がグリルの様子を窺うように腰を落とす。"
    },
    {
        "message": "岸田の手の動きが止まる。"
    },
    {
        "message": "俺は片目をつむり照星に集中する。"
    },
    {
        "name": "岸田",
        "message": "「ぐっ！？」"
    },
    {
        "message": "撃発の音と共にシャフトはグリルを横切り、岸田の上腕部を射抜く。"
    },
    {
        "message": "腕を貫く金属の矢には一瞥をくれただけで、岸田はこちらを睨みつける。眼差しは熱を感じるほどにぎらついているが、口元だけはニヤリと笑っていた。"
    },
    {
        "name": "岸田",
        "message": "「外したな」"
    },
    {
        "message": "猛然と駆け寄ってくる岸田に、俺は慌ててクロスボウの弦を引いた。"
    },
    {
        "message": "銃声はしない。恵は何をしている。俺は弦を引ききりシャフトを載せ、飛び道具相手に躊躇いもなく迫り来る岸田に照星を向ける。"
    },
    {
        "name": "岸田",
        "message": "「しゃあああああっっ！！」"
    },
    {
        "message": "撃発の寸前、閃いた長剣にクロスボウが跳ね上げられ、飛び出したシャフトが天井に突き立つ。"
    },
    {
        "message": "続けざまの二撃目を、俺はクロスボウの台尻で受け止める。"
    },
    {
        "name": "恭介",
        "message": "「ぐはっ！」"
    },
    {
        "message": "クロスボウごと俺は後方へ飛ばされる。仰向けに倒れたところへ、起き上がる暇もなく渾身の一撃が振り下ろされる。"
    },
    {
        "name": "恭介",
        "message": "「ぐっ！」"
    },
    {
        "message": "薪に斧が食い込むような音がした。横に倒したクロスボウを両手で握りなおしていたが、それでも衝撃を支えきれず、刃先が目の前まで降りてくる。"
    },
    {
        "name": "恭介",
        "message": "「ぎ、ぎぎ・・・」"
    },
    {
        "name": "岸田",
        "message": "「くっ・・・！」"
    },
    {
        "message": "刃が木製の台尻に食い込んでしまったらしい。岸田は長剣を振りかぶるのをあきらめ、押し切るように体重を掛けてくる。"
    },
    {
        "message": "覆いかぶさるような圧力に、俺は必死に抵抗するが、台尻は徐々に降りてくる。"
    },
    {
        "message": "腕が震える。微妙に揺れる刃先が俺の鼻先をチクチクと突っつく。"
    },
    {
        "name": "岸田",
        "message": "「そら、刺さるぞ。今すぐ死ぬぞ」"
    },
    {
        "name": "恭介",
        "message": "「ぐっ・・・」"
    },
    {
        "message": "俺のこといたぶって楽しんでるんじゃなかったのかよ・・・。"
    },
    {
        "message": "・・・だったら一気に殺っちまっていいのかよ！"
    },
    {
        "name": "恭介",
        "message": "「っあああ！！」"
    },
    {
        "name": "岸田",
        "message": "「！？」"
    },
    {
        "message": "気合い一閃、押し込まれる力を横に流す。岸田の上体が崩れた瞬間、俺は床を転がり岸田の下から脱した。"
    },
    {
        "message": "息をつく暇もなく俺は床から跳ね起きた。岸田は台尻に刺さった長剣には目もくれず、腕を貫くシャフトを掴んで引き抜く。"
    },
    {
        "name": "岸田",
        "message": "「ぐっ、ぎぎ・・・がああああっっっ！！！」"
    },
    {
        "message": "血塗られたシャフトを握りしめ、岸田はぎらついた瞳を俺に向ける。苦痛も憤怒も狂気の色に塗りつぶされていた。"
    },
    {
        "message": "動け、動けよ、俺の足・・・っ！"
    },
    {
        "message": "硬直した体を叱咤しながら、俺はテーブルを蹴り上げて壁にする。"
    },
    {
        "message": "その陰で椅子の背もたれを掴み、テーブルを回り込んでくる奴の顔面に目がけて一撃を食らわせる。"
    },
    {
        "message": "岸田は腕を上げて椅子の一撃を防ぐと、もう一方の手で握られたシャフトを無造作に突きだした。太い金属の先端が俺の腕にめり込む。"
    },
    {
        "name": "恭介",
        "message": "「ぐあっ！？」"
    },
    {
        "message": "さらにもう一度、アイスピックで氷を割るように呆気なく、俺の腕を突き刺す。"
    },
    {
        "name": "恭介",
        "message": "「あっ、あっ、ああああっっ！！」"
    },
    {
        "message": "俺は椅子を放り出してもんどり打った。"
    },
    {
        "message": "『痛い』『痛い』『痛い』"
    },
    {
        "message": "信じられない痛みが意識を浸食していく。打算も計算も戦意も一瞬で消え失せた。"
    },
    {
        "name": "恭介",
        "message": "「ああぁぁああああうああぅぅあああっっっ！！」"
    },
    {
        "message": "振り上げられる金属の先端。全身を耐えがたい苦痛と恐怖に染め抜かれ、俺は奇声を上げてその場から逃げ出した。"
    },
    {
        "name": "恭介",
        "message": "「あっ！！」"
    },
    {
        "message": "ロビーまで逃げてきて何もないところで蹴つまずく。腰に力が入らず、俺はそのまま床に倒れ伏した。"
    },
    {
        "message": "背後にゆっくりと近づいてくる足音。振り返らずとも、赤く染まったシャフトを握る岸田の姿が脳裏にまざまざと描かれる。"
    },
    {
        "name": "恭介",
        "message": "「い、いやだ、助けてくれ、頼む、助け・・・っ！」"
    },
    {
        "message": "痛みが俺を臆病者にする。"
    },
    {
        "message": "足はガクガクと震えるばかりで、立ち上がることができない。俺は無駄と知りつつも許しを乞いながら、必死に床を這いずる。"
    },
    {
        "name": "恭介",
        "message": "「やめてくれ、もう刺さないで」"
    },
    {
        "name": "恭介",
        "message": "「あぉうああっっ！！？？　さ、刺した、また刺したっっ！！」"
    },
    {
        "message": "シャフトがふくらはぎを裏側から突き通した。焼けるような感覚はすでに痛みですらなかった。"
    },
    {
        "message": "泣き叫びながら狼狽する俺を、岸田はシャフトを引き抜きながら憐れむような眼差しで見下ろす。"
    },
    {
        "name": "岸田",
        "message": "「どうした、泣くだけか？　それで助かるとでも思っているのか？　もう他にやることはないのか？」"
    },
    {
        "name": "恭介",
        "message": "「た、たす、熱いっ、もう、やめ、死ぬ、死んじまう」"
    },
    {
        "name": "岸田",
        "message": "「・・・・・・」"
    },
    {
        "name": "岸田",
        "message": "「そうか」"
    },
    {
        "name": "岸田",
        "message": "「お前はここまでのようだな」"
    },
    {
        "message": "岸田は静かに告げると、手にしたシャフトを振り上げる。"
    },
    {
        "name": "岸田",
        "message": "「電池の切れた玩具に用はない」"
    },
    {
        "message": "俺の太ももに振り下ろされる金属の先端。さらに二度、三度、そのたびに筋肉は痙攣して鮮血が水飲み場の蛇口のように細く噴き上がる。"
    },
    {
        "name": "恭介",
        "message": "「ぎゃおうああああっっっ！！！」"
    },
    {
        "message": "頭の中で火花が散った。許容しきれない痛みに脳内の神経が焼き切れる。"
    },
    {
        "message": "奴の顔面を蹴りつけていたのは、ほとんど反射のようなものだった。"
    },
    {
        "message": "不意の攻撃に遭い、岸田は顔をかばって立ち上がり、数歩を後ずさる。その間にも俺は死にものぐるいで床を這いずる。"
    },
    {
        "message": "死ぬ。殺される。このまま黙っていたら確実に躊躇なく殺される。"
    },
    {
        "message": "体力では勝負にならない。圧倒的な力の前にねじ伏せられ、くびり殺される。何か武器はないか、殺られる前に奴を殺せる道具はっ！"
    },
    {
        "name": "恭介",
        "message": "「いづっ！！」"
    },
    {
        "message": "穴だらけの太ももには、シャフトが突き立ったままになっていた。"
    },
    {
        "name": "恭介",
        "message": "「・・・・・・」"
    },
    {
        "message": "俺は目をつむり、それに手を掛ける。"
    },
    {
        "name": "恭介",
        "message": "「っっっっっっいいいいい！！！」"
    },
    {
        "message": "一気にやった方が痛みも少ないなんて誰が言ったんだああ！！"
    },
    {
        "message": "俺は岸田に向き直り、相変わらず床にへたり込んだまま、俺自身の血で濡れたシャフトを握りしめる。"
    },
    {
        "message": "岸田は自分に向けられたシャフトの先端を見つめる。間合いを詰めてくる気配はなかったが、その表情には恐怖も警戒もあざけりさえも浮かんでいなかった。"
    },
    {
        "name": "岸田",
        "message": "「それで？」"
    },
    {
        "message": "無表情のまま告げる。"
    },
    {
        "name": "岸田",
        "message": "「次はどうする気だ？」"
    },
    {
        "message": "シャフトの切っ先は震えていた。"
    },
    {
        "name": "岸田",
        "message": "「立ち上がることもできずにいる奴が、刃物を手にしただけでどうにかなるのか？」"
    },
    {
        "name": "岸田",
        "message": "「相手の方から親切に刺されてくれるとでも思っているのか？」"
    },
    {
        "name": "岸田",
        "message": "「ただ構えているだけの刃物に、俺が自分から胸を押しつけてくるとでも？　そんなことを期待しているのか？」"
    },
    {
        "message": "奴の言うとおり、シャフトを取り返したところで足をやられていては時間稼ぎにしかならない。"
    },
    {
        "message": "何とか立ち上がれないか。それを試す余裕すらなく、穴だらけにされた太ももは脈に合わせて間断なくうずく。"
    },
    {
        "name": "恭介",
        "message": "（づづっ・・・先にやられた腕の方も痛みが増してきた）"
    },
    {
        "message": "気が狂いそうなほどの激痛が、むしろ俺を恐怖や硬直から救っていた。だからといって逃げ出すこともできなければあまり意味はないのだが。"
    },
    {
        "message": "とにかくシャフトだけじゃ駄目だ。他の何かを・・・でもこの場からは動けない。俺は意味もなくポケットをまさぐる。"
    }
]