[
    {
        "message": "船底はここで行き止まりだ。もう逃げようがない。"
    },
    {
        "message": "このまま一方的に殺されるのか・・・！"
    },
    {
        "message": "せめて奴だけでも道連れにしてやる。うまく行けば同士討ちをネタにこの場を逃れられるかもしれない。"
    },
    {
        "message": "俺は重油のバルブを開いた。"
    },
    {
        "name": "恭介",
        "message": "「止まれ！！！」"
    },
    {
        "message": "警告しながら、オイルライターの蓋を開いてみせる。"
    },
    {
        "name": "恭介",
        "message": "「それ以上近づくと、お前も一緒に丸焼けだぞ！！！」"
    },
    {
        "name": "岸田",
        "message": "「そうか」"
    },
    {
        "message": "だが、岸田の反応はひどく淡泊なものだった。"
    },
    {
        "name": "岸田",
        "message": "「ならやってみろ」"
    },
    {
        "message": "呆気ないくらいに、行動を肯定されてしまう。"
    },
    {
        "name": "岸田",
        "message": "「まったく、燃料をこんなにしやがって」"
    },
    {
        "name": "岸田",
        "message": "「ちゃんと自分で始末しろよ」"
    },
    {
        "message": "そう言うと、岸田は俺と同じくカチリとオイルライターの蓋を開いた。"
    },
    {
        "name": "恭介",
        "message": "「え？」"
    },
    {
        "name": "岸田",
        "message": "「後かたづけの手伝いくらいはしてやるよ」"
    },
    {
        "message": "火を点じて投げ込まれるオイルライター。まるでスローモーションのように、重油でひたひたになった床へと落ちていく。"
    },
    {
        "message": "岸田はあっさりと引き返し、循環室へのハッチを閉じた。"
    },
    {
        "name": "恭介",
        "message": "「！！？？」"
    },
    {
        "message": "炎の壁は高く天井まで舐める。目の前の事態に、俺はただ呆然とするしかなかった。"
    },
    {
        "message": "もう逃げ場はない。"
    },
    {
        "message": "何者も今の俺を救うことはできない。"
    },
    {
        "message": "確定した死。"
    },
    {
        "message": "体から力が抜け、俺は床に膝を突いた。"
    },
    {
        "message": "重油の燃焼温度は千度を超える。"
    },
    {
        "name": "恭介",
        "message": "「・・・だめだこりゃ」"
    },
    {
        "message": "<S0>じきに俺は骨まで焼き尽くされるだろう。<W60>"
    }
]