[
    {
        "name": "女のコ",
        "message": "「んっ！　ん、んんっ！！　くっ、あはぁ！！」"
    },
    {
        "message": "隔壁のハンドルが固定されていることをバリケード越しに確認してから、俺は大浴場の脱衣所に足を踏み入れる。"
    },
    {
        "name": "女のコ",
        "message": "「あ、うぁ！　うっ、うっ、んんぅ！　はぁ、はぁ、あぁぁ・・・」"
    },
    {
        "message": "声は浴室から聞こえてくる。"
    },
    {
        "message": "まさか・・・"
    },
    {
        "message": "こんな息づかいが明乃の口からもれるなんて想像もできない。だが、浴室の喘ぎ声は確かに聞き慣れた明乃のものだった。"
    },
    {
        "name": "明乃",
        "message": "「あ！　あ！　だ、だめっ！！　こんなのじゃ・・・あああっ！！」"
    },
    {
        "message": "俺は街灯に引かれる羽虫のように、浴室へと吸い寄せられていく。"
    },
    {
        "name": "明乃",
        "message": "「ん・・・んんっ！！　うくっ、あ、あはぁ！！」"
    },
    {
        "message": "想像すらできなかった光景が、俺の目の前に現実として横たわる。"
    },
    {
        "message": "冷たく固いタイルに俯せになり、嫌らしくお尻を突きだして懸命に自分の股間をさする少女は・・・見間違いようもなく俺の幼なじみ、明乃本人だった。"
    },
    {
        "message": "明乃がこんな・・・自分で慰めるにしてもこんな・・・淫らな腰つきをしてなくても。"
    },
    {
        "name": "明乃",
        "message": "「あ、あ、だめ、これじゃ全然・・・はぁん！！　足りない、足りないよぉ！！　あぁぁぁん！！」"
    },
    {
        "message": "いったいどうしたんだ。妙な薬でも打たれたのか。それとも岸田に加えられた刺激が残り火となって明乃の体を内側から焦がすのか。"
    },
    {
        "name": "恭介",
        "message": "（くっ・・・）"
    },
    {
        "message": "そこまで想像して俺は下唇を噛みしめる。奴の指が舌が陰茎が今も明乃を責めさいなんでいるなんて、そんなことは我慢できない。"
    },
    {
        "message": "何もこんなによがることないだろ。この状況で俺が最初に感じたのは、身をよじる明乃に対する嫉妬だった。"
    },
    {
        "message": "だが、視線はさっきから明乃の股間に釘づけになっている。いつ着替えたのか、明乃は大人びた黒の下着を身につけていた。"
    },
    {
        "message": "露骨な女の装いは明乃にはまだ痛々しく、そのちぐはぐさが逆にタブーめいた嫌らしさをかき立てている。"
    },
    {
        "message": "・・・いや、違う。これはパンツじゃない。表面は皮のような光沢があり、股の途中から大きく開き、お尻の穴が剥き出しになっている。"
    },
    {
        "message": "こういう下着には付き物のレース模様もなかった。"
    },
    {
        "name": "明乃",
        "message": "「ああっ！！　誰か、誰かぁ！！　これ剥がしてぇぇ！！」"
    },
    {
        "message": "明乃はもどかしそうに下着の縁に手を掛けるが、どう固定されているのか、下着は明乃の腰から離れようとしない。"
    },
    {
        "name": "明乃",
        "message": "「あぁぁぁ・・・だめ、もうだめぇ・・・はぁ、はぁ、はぁ」"
    },
    {
        "message": "明乃は嘆息して下着の上から自分の割れ目を激しく擦る。その仕草はまるで、股間を掻きむしるようでもあった。"
    },
    {
        "message": "明乃が作業・・・そう、一心不乱にその作業を続ける一方で、俺はかすかに続くモーター音のようなものに気づく。"
    },
    {
        "message": "内の音としてはありふれていて、今まで気にも止めなかったが、その音は明乃の指の動きに合わせて低く高くうねっていた。"
    },
    {
        "message": "音の源は明乃の腰の辺りにあるらしい。皮の下着にモーター音、剥き出しになったお尻の穴、それらがつながる糸は一本しかない。"
    },
    {
        "name": "明乃",
        "message": "「うん、ぇはあ・・・だ、だめぇ、こんなのじゃ足りないぃぃ！！」"
    },
    {
        "message": "俺は生唾を飲み込んだ。この音が明乃に届くことを望んでいたが、明乃は微妙に続く刺激に身をよじるばかりで俺の存在には気づかない。"
    },
    {
        "message": "きっかけを待つことなく、俺は浴室のドアをカラリと開けた。"
    },
    {
        "name": "明乃",
        "message": "「あ・・・」"
    },
    {
        "message": "明乃は焦点の合わない瞳で俺を振り返る。"
    },
    {
        "name": "明乃",
        "message": "「・・・ぁ・・・恭ちゃ・・・ん・・・」"
    },
    {
        "message": "体裁をつくろう気力もないようだ。明乃はお尻を突きだしたまま俺をぼんやりと見上げる。汗ばんだ額に張りつく前髪もかき上げようとはしない。"
    },
    {
        "name": "明乃",
        "message": "「い、いや・・・ちがう、これちがぅ・・・」"
    },
    {
        "message": "否定にも力がこもらない。言葉とは裏腹に、明乃の疲れ切った体は、股間に突き刺さったバイブの振動にだけはピクンピクンと反応している。"
    },
    {
        "message": "無言で立ちつくす俺を、明乃は湯上がりのような気だるさで見つめ続ける。"
    },
    {
        "name": "明乃",
        "message": "「はぁ、はぁ、はぁ・・・っ、ぅ・・・はぁ・・・」"
    },
    {
        "name": "明乃",
        "message": "「やだ・・・指、止まんな・・・んんっっ、もうちょっとで・・・」"
    },
    {
        "name": "明乃",
        "message": "「見ないで、お願い・・・恭ちゃん・・・」"
    },
    {
        "message": "岸田か。これも岸田の仕業か。"
    },
    {
        "message": "下層に閉じこめられながら、なおも俺たちを操ろうというのか。"
    },
    {
        "name": "明乃",
        "message": "「ぁ・・・はぁ・・・・・・」"
    },
    {
        "message": "やがて明乃の瞳に艶めかしい色が混ざり始めた。明乃は瞼を薄く閉じる。"
    },
    {
        "name": "明乃",
        "message": "「恭ちゃん・・・」"
    },
    {
        "name": "明乃",
        "message": "「お願い・・・あたし、もうだめ・・・」"
    },
    {
        "name": "恭介",
        "message": "「・・・！」"
    },
    {
        "message": "身もだえする明乃を前にして、モニタールームで見た光景が脳裏をよぎる。"
    },
    {
        "message": "岸田に責められながらも股を濡らしていた明乃の姿が。"
    },
    {
        "message": "岸田への憎悪と同じだけの憤りが、いやらしく女を匂わせている明乃の方へと傾いていく。"
    },
    {
        "name": "明乃",
        "message": "「あたしの、からだ・・・熱くて・・・おかしくなりそう・・・お願い、恭ちゃん・・・助けて・・・」"
    },
    {
        "name": "明乃",
        "message": "「もう・・・げんか・・・っっ・・・限界・・・助けて、恭ちゃ・・・ぁぁ・・・た、たす・・・」"
    },
    {
        "name": "恭介",
        "message": "「・・・」"
    },
    {
        "name": "明乃",
        "message": "「はぁ、はぁ、はぁ・・・んっっ、あはぁ・・・もう、がまんできなぃ・・・」"
    },
    {
        "name": "恭介",
        "message": "「・・・」"
    },
    {
        "name": "明乃",
        "message": "「お、おねがい・・・そんな、黙って見てるなんて・・・ぅぅんっ」"
    },
    {
        "name": "恭介",
        "message": "「・・・」"
    },
    {
        "name": "恭介",
        "message": "「お尻をこっちに向けろよ」"
    },
    {
        "name": "明乃",
        "message": "「っっ・・・え、え・・・？」"
    },
    {
        "name": "恭介",
        "message": "「このままでいるのはつらいだろ？」"
    },
    {
        "name": "明乃",
        "message": "「あ・・・う、うん・・・」"
    },
    {
        "message": "明乃はお仕置きを待つようにお尻を突きだしたまま、溶けるような瞳で俺を見つめる。"
    },
    {
        "message": "助ける・・・その言葉が俺を突き動かすきっかけになった。俺は明乃のお尻の前に膝を突く。皮の下着で固められた明乃の敏感な部分へ指を伸ばす。"
    },
    {
        "name": "明乃",
        "message": "「あ、ちがっ、そこじゃ・・・ない」"
    },
    {
        "message": "下着を隔てた刺激ではもうどうにもならないらしい。明乃は両手でお尻の割れ目を開いてみせた。こぢんまりとすぼまったお尻の穴が俺の鼻先に突きだされる。"
    },
    {
        "name": "明乃",
        "message": "「お願い、こっちで・・・して」"
    },
    {
        "message": "言うなり、明乃は顔を真っ赤にする。いきなりお尻をおねだりしている自分が恥ずかしくてたまらなくなったのだろう。"
    },
    {
        "message": "皮の下着はどういう構造になっているのか、外すきっかけすら見つからない。下着自体にも薄い金属が仕込んであるらしく、ハサミなどで断ち切るのも無理のようだ。"
    },
    {
        "name": "明乃",
        "message": "「恭ちゃん、お願い・・・早く突いて・・・」"
    },
    {
        "message": "じれた明乃が泣きそうな声をもらす。今も下着に付属したバイブは明乃の体内で震えている。確かに、この状態でやるとしたらお尻しかない。"
    },
    {
        "name": "恭介",
        "message": "（お尻・・・明乃のお尻・・・）"
    },
    {
        "message": "口の中で際限なく唾液が溢れてくる。本人が頼んでいるんだからいいんだよ、な。"
    },
    {
        "message": "俺は自分のズボンに手をかけるが、気ばかり焦ってうまくベルトを外せない。指が震えていたずらにカチャカチャと音を立てる。"
    },
    {
        "name": "明乃",
        "message": "「ちがっ！　待って、恭ちゃん、そんな・・・いきなりじゃなくて、その・・・」"
    },
    {
        "name": "明乃",
        "message": "「最初は、優しくして・・・」"
    },
    {
        "name": "恭介",
        "message": "「あっ・・・ああ」"
    },
    {
        "message": "俺は慌てて頷く。ひとつまみだけ残っていた理性が、人差し指を唾液で湿らせる。"
    },
    {
        "name": "明乃",
        "message": "「あぅんっ！？」"
    },
    {
        "name": "恭介",
        "message": "「ま、まだ何もやってないぞ！？」"
    },
    {
        "name": "明乃",
        "message": "「ぅぅん、ぅ・・・恭ちゃん、息が・・・」"
    },
    {
        "message": "みっともないくらい荒くなっていた鼻息が、明乃のお尻の穴に吹きかけられていたらしい。俺は慌てて自分の鼻を両手で覆う。"
    },
    {
        "message": "だが待てよ。今は明乃に何をやっても許されるんじゃないだろうか。むしろその方が明乃にとっても・・・"
    },
    {
        "message": "悪戯心がむくむくと頭をもたげてくる。"
    },
    {
        "name": "明乃",
        "message": "「んっ、く」"
    },
    {
        "message": "俺は手のひらをペタリと明乃のお尻にくっつける。右手も左手も。そして、明乃自身がやってみせたように、俺はお尻の割れ目を開いた。"
    },
    {
        "name": "明乃",
        "message": "「あっ・・・ぁ・・・そんな、見ないでぇ・・・」"
    },
    {
        "message": "お尻の穴を空気にさらされ、明乃が恥ずかしさのあまり身をよじる。俺は目が中央に寄るほど明乃のお尻に顔を近づけ、唇をすぼめた。"
    },
    {
        "name": "恭介",
        "message": "「ふ、ふぅぅ」"
    },
    {
        "name": "明乃",
        "message": "「きゃううんっっ！！？？」"
    },
    {
        "message": "興奮で息が震える。だが、触れるか触れないという刺激に明乃は悲鳴を上げた。"
    },
    {
        "name": "明乃",
        "message": "「い、いやぁ！！　あっ！？　ひぃ、ひゃううんんっっっ！！」"
    },
    {
        "name": "恭介",
        "message": "「ぅ、ぅ、ふぅぅ」"
    },
    {
        "name": "明乃",
        "message": "「ひぃぃぃぁああっ！！？？　だめ、そんなのだめだよぉ、それじゃな・・・ぁぁぁあああっっ！！？？」"
    },
    {
        "message": "ぬぷっ。"
    },
    {
        "name": "明乃",
        "message": "「あひぃぃぃぃいいい！！！！」"
    },
    {
        "message": "ひくひくと痙攣するお尻の穴に前触れもなく指を押しつけると、明乃は仰け反るほどに悲鳴を上げた。"
    },
    {
        "message": "しわしわとして不思議な感触のするお尻の穴を、俺は揉むようにほぐしていく。"
    },
    {
        "name": "明乃",
        "message": "「あっ！　あっ！　平気だから、早くそのまま入れてぇ！！」"
    },
    {
        "message": "優しくしてと言った舌の根も乾かぬうちに、明乃は嬌声を上げる。緊張に張りつめたお尻の穴へ、俺は指を突き立てた。"
    },
    {
        "name": "明乃",
        "message": "「くぅぅぅ！！　ぅぅぅん・・・ぅ、ふぅ、ふ・・・っっっっ！！」"
    },
    {
        "message": "明乃のお尻の肉がキュッと強ばる。お尻の穴も、俺の指を吐き出そうとするようにきつく締まった。"
    },
    {
        "name": "明乃",
        "message": "「ぅ・・・ぁぁ・・・は、入ってる・・・あたしの中に、入ってる・・・ぅぅ！！」"
    },
    {
        "message": "指を根元まで入れるまでもなく、指先が何にも触れなくなる。ここは大腸？　直腸とも言うんだったかな？"
    },
    {
        "message": "俺の指先はすでに明乃の内臓まで入り込んだわけか。何か新鮮な感動が込み上げてくる。"
    },
    {
        "message": "肛門は意外と厚みがあった。俺は突き入れた指を３６０度回転させ、異物の侵入に強ばる尻穴をまんべんなくほぐしていく。"
    },
    {
        "name": "明乃",
        "message": "「あ、あ、お尻がぐりぐりされて、んあぁ、いい、これいい」"
    },
    {
        "name": "明乃",
        "message": "「はぁ、はぁ、はぁ、もっと、もっとして、ぐりぐりして、もっとぉ！」"
    },
    {
        "message": "普段からは考えられないような言葉が、明乃の口から飛び出してくる。明乃もほとんど無意識に口走っているのだろう。"
    },
    {
        "message": "だらしなく開かれた口からはよだれがこぼれ、床のタイルに粘液質の水たまりを作っている。"
    },
    {
        "name": "明乃",
        "message": "「あっ、ふぁぁ！？　う、あ・・・やだ・・・」"
    },
    {
        "message": "突然指を引き抜かれて、明乃は鼻にかかった声をもらした。熱い吐息が明乃の喉を行き来する。"
    },
    {
        "message": "冗談じゃない。明乃は白目をむくほどよがっていたが、これ以上指だけでは、俺の方が我慢できない。"
    },
    {
        "name": "恭介",
        "message": "（お、俺も俺も）"
    },
    {
        "message": "入れたい。明乃の中に、いきり立つ先端を突き入れたい。もう穴ならどれでもいい。"
    },
    {
        "message": "俺はベルトを外すことさえもどかしく、ズボンのチャックを降ろした。人体の一部とは思えないほど硬直したモノがパンツの合わせ目を押しのけて屹立する。"
    },
    {
        "message": "俺はオスの気ぜわしさで明乃の腰にまたがった。ぎちぎちと音を立てるほど固くなった先端が、明乃の尻穴に押し当てられる。"
    },
    {
        "name": "明乃",
        "message": "「んっ！　なにこれ、固い！」"
    },
    {
        "message": "逃げるお尻をしっかりとつかまえる。"
    },
    {
        "name": "恭介",
        "message": "「何って言われても、これだよこれ」"
    },
    {
        "name": "明乃",
        "message": "「こ、こんなに固いの・・・？　あぁぁ、同じくらい固いぃ・・・！」"
    },
    {
        "message": "前の穴に入っているバイブと比較されているのだろうか。お尻の穴というただでさえ敏感な部分に、生物的でない固さを押し当てられ、明乃の背中が小刻みに震える。"
    },
    {
        "message": "固いと言われようと、俺はもう辛抱たまらない。この指が記憶した感触を辿るように、俺は欲望で張りきったモノで、明乃の尻を深々と割っていく。"
    },
    {
        "name": "明乃",
        "message": "「あ、あ、広がって・・・んんんっっっ！！！」"
    },
    {
        "name": "明乃",
        "message": "「んんんぅ！！！　うっ！　うくっ！　くぅぅぅ！！！」"
    },
    {
        "name": "明乃",
        "message": "「ぐっ！　ぃぃぃい！　うっ、うっ、づっっっっ！！」"
    },
    {
        "message": "急に無口になった。と思ったら、歯を食いしばっている。"
    },
    {
        "message": "俺は明乃の体内への侵入を止めた。だがモノの固さはすぐには抜けない。むしろ根元を絞られるようなきつさに輪を掛けていきり立つ。"
    },
    {
        "name": "明乃",
        "message": "「はぁ、はぁ・・・大丈夫・・・このまま・・・もう、楽になったから・・・」"
    },
    {
        "message": "そう言いながらも明乃は苦痛に顔をしかめ、額からは玉のような汗を滲ませる。"
    },
    {
        "name": "明乃",
        "message": "「中途半端で、終わる方が・・・あ、後でつらくなるから・・・」"
    },
    {
        "message": "バイブはなおもブブブと震動している。その動きは低調で、明乃は解放されてから、もしくはずっと以前から、女の部分に微妙すぎる刺激を加えられ続けている。"
    },
    {
        "name": "明乃",
        "message": "「もうおかしくなりそう・・・だからお願い・・・」"
    },
    {
        "message": "明乃はおねだりするように、犯されている途中のお尻を俺の腰へと寄せた。"
    },
    {
        "name": "明乃",
        "message": "「イかせて・・・お尻でイかせて・・・」"
    },
    {
        "message": "明乃の懇願に涙声が混じる。もし明乃の口から出たのが拒絶だったとしても、この声で言われては自分を押しとどめることなどできはしない。"
    },
    {
        "message": "俺は何も言わずに、一段と固さを増したモノを明乃の尻穴にねじ込む。"
    },
    {
        "name": "明乃",
        "message": "「あ、あ、あ、あああああっっ！！！」"
    },
    {
        "message": "明乃は身を仰け反らせる。汗なのか涙なのか、透き通った滴が明乃の頬を伝った。"
    },
    {
        "name": "明乃",
        "message": "「入ってくる！　まだ入ってくる！　あっ、ふあっ、あぅぅぅ！！　ま、まだ！？　こんなに、あたしのお腹に・・・ぁぁ・・・」"
    },
    {
        "message": "最も奥へ。むっちりとした尻肉が俺の腰に密着する。汗ばんだ肌が吸いつきあう。"
    },
    {
        "name": "明乃",
        "message": "「お尻が、お尻が、こんなに開いて！　裂ける、裂けちゃう！　ひぃぃいいいっっ！！？？」"
    },
    {
        "message": "根元まで突き刺したモノを、ゆっくりと引き抜いていく。お尻のヒダがずるりとめくれ上がり、明乃の腸内のピンク色が外気にさらされる。"
    },
    {
        "name": "明乃",
        "message": "「ああっ！？　お腹が！　お腹の中が！　引きずられてるぅ！！　ふあああっっ！！」"
    },
    {
        "message": "明乃が悲鳴に近い声を上げる。だが俺は許さない。明乃の尻肉を指が食い込むほど捕らえ、腰を打ちつける。"
    },
    {
        "message": "明乃には酷なまでに固くなったモノが、明乃の尻穴を直腸内まで押し広げる。"
    },
    {
        "name": "明乃",
        "message": "「うくぅ！！　うっ・・・っっ・・・」"
    },
    {
        "message": "もっと明乃に声を上げさせたい。我を忘れての喘ぎ声、じれてむせび泣く声、意表を突かれて息をのむ気配。ありとあらゆる声をその唇から絞りだしたい。"
    },
    {
        "message": "繰り返し繰り返し、俺は明乃の尻を犯し続けた。"
    },
    {
        "name": "明乃",
        "message": "「・・・っっ・・・あぅん！！　あう、あはぁ！！　ああっ！！　ああっ！！　あぁぁぁ！！」"
    },
    {
        "message": "明乃が初めて尻を犯されているのも忘れかけていた。明乃の体内で感じるバイブの振動が半ばそうさせた。"
    },
    {
        "message": "見てもいないのに、膣内にあるバイブの様子が網膜に映し出される。遠慮や気づかいが蒸発していく。"
    },
    {
        "message": "単に挿入という役目だけなら不必要なほど固く怒張するモノで、俺は執拗に明乃の尻穴を抉る。"
    },
    {
        "name": "明乃",
        "message": "「あっ、あっ、うあ・・・んっ、あぁ・・・んくっ、んっ、んっ、あはぁ」"
    },
    {
        "message": "明乃の息づかいが変わった。"
    },
    {
        "name": "明乃",
        "message": "「あ、あぁぁ・・・あたし、されてる・・・お尻、されてるよぉ・・・ああ、こんなにされてるっ」"
    },
    {
        "message": "喘ぎ声が明乃の鼻から抜ける。おねだりするような甘い吐息が、喘ぎ声の途切れ目に明乃の唇から漏れる。"
    },
    {
        "message": "打ち鳴らされる下半身は滴るほどの体液で湿っているというのに、口の中はからからに乾いていた。"
    },
    {
        "message": "明乃も似たような状況なのだろうか。喘ぎ続けているから俺よりも口の中が粘ついているだろうか。"
    },
    {
        "name": "明乃",
        "message": "「ん！　・・・んぁ・・・ああ！　ああ！　んん・・・っ！　あ、はぁ！！」"
    },
    {
        "message": "明乃はぐずるように喉の奥を甘く震わせる。オスの動きを乾くように求めている。"
    },
    {
        "name": "明乃",
        "message": "「して、して、もっとしてぇ！！　痛いのもっとしてぇ！！」"
    },
    {
        "message": "俺は夢中になって、責められることに未熟な尻穴をさんざんに貫く。"
    },
    {
        "name": "明乃",
        "message": "「あっ、あっ、やめないで、このまま、イかせて、たくさんイかせて！！　んあああっ！？　いい！　今の！　もっと！」"
    },
    {
        "message": "むさぼるように尻穴を犯されながら、明乃は普段からは考えられないような嬌声を上げた。"
    },
    {
        "name": "明乃",
        "message": "「ん、んぅぅ・・・」"
    },
    {
        "message": "やがて明乃は身を反らせて硬直する。かすかな痙攣が何度も明乃の手足に走る。"
    },
    {
        "message": "尻穴がきゅっきゅっとすぼまる。明乃の体の緊張が、俺のモノを心地よく締めつける。"
    },
    {
        "message": "正気が飛んだ。俺は明乃の尻穴を激しく摩擦しながら、込み上げてくる欲望を明乃の内臓へ直接飛び散らせた。"
    },
    {
        "name": "明乃",
        "message": "「ん・・・ぁ・・・っっ・・・」"
    },
    {
        "message": "腸内に射精されても、明乃の緊張は終わらない。明乃は、つま先立つような声をたなびかせる。"
    },
    {
        "name": "明乃",
        "message": "「っ・・・んっ、ぅ・・・・・・」"
    },
    {
        "message": "やがてビクンと大きく身を震わせると、あとは呆気ないほど明乃の体から力が抜ける。"
    },
    {
        "name": "明乃",
        "message": "「・・・ぁ・・・・・・」"
    },
    {
        "message": "明乃はくたりと首を垂れ、床のタイルに寝そべった。行為の激しさとは逆に、安らかな寝顔を浮かべている。"
    },
    {
        "name": "明乃",
        "message": "「あ・・・ぇあ・・・」"
    },
    {
        "message": "ちょっと白目を剥いてはいるが。"
    },
    {
        "message": "明乃から身を離した途端、汗ばんだ肌に張りつくシャツが気になり始める。それでなくとも浴場だけに湿気は高い。"
    },
    {
        "message": "今はタイルに伏せているが、明乃の下半身の悲惨さはひどいものだ。自分でやっておきながら何だが、このままでは不快な感触に困るだろう。"
    },
    {
        "message": "取りあえず、備えられた手ぬぐいを湯に浸して自分のモノを拭う。尻を犯したのにそのままモノを仕舞うほど俺は豪気ではない。"
    },
    {
        "message": "チャックを上げ、常態に戻る。次は明乃の体を綺麗にしなくてはならない。"
    },
    {
        "message": "湯浴みでもさせるのが一番手っ取り早いのだが、寝ている明乃の服を勝手に脱がせるわけにもいかない。"
    },
    {
        "name": "恭介",
        "message": "（・・・下だけでも何とか）"
    },
    {
        "message": "痛々しいほど充血している明乃の尻穴からは、最奥に放ったはずの白濁が溢れてきている。"
    },
    {
        "message": "俺は湿らせたタオルを手に明乃の尻に屈み込む。タオルは先ほど自分のモノを拭ったものとはさすがに別だ。"
    },
    {
        "message": "タオルの端をこよりにして、まだわずかに開いている尻穴を拭う。"
    },
    {
        "name": "明乃",
        "message": "「あっ・・・ひぃあ！？」"
    },
    {
        "message": "弛緩していたはずの明乃の体が電気でも流されたかのようにビクンと震えた。びっくりして目を見張る。"
    },
    {
        "name": "恭介",
        "message": "「いや、ほら、このままだと汚いから」"
    },
    {
        "message": "俺は慌てて手にしたタオルを示し、イタズラしたわけではないことを証明する。"
    },
    {
        "message": "明乃が吐息を漏らす。納得してくれたようだが、すぐに明乃は顔から首筋までを真っ赤に染めた。"
    },
    {
        "message": "まだ足元がおぼつかないながらも、自分のお尻を手でかばいつつ床から立ち上がる。"
    },
    {
        "message": "よくよく考えてみたら、服を脱がせるよりも尻穴をほじくる方がひどいよな。まだ欲情の余熱に当てられているのか、その辺りの感覚があやふやだ。"
    },
    {
        "name": "明乃",
        "message": "「そ、それは自分でするから。恭ちゃんは恭ちゃんで自分の方を・・・」"
    },
    {
        "message": "俺のモノがすでにズボンの中に収まっていることを知り、明乃は目を丸くする。"
    },
    {
        "name": "恭介",
        "message": "「違う、もう綺麗にしたから、うん」"
    },
    {
        "name": "明乃",
        "message": "「あ、そうなんだ・・・」"
    },
    {
        "name": "恭介",
        "message": "「体、大丈夫か・・・？」"
    },
    {
        "name": "明乃",
        "message": "「うん・・・もうつらくない。ただ震えてるって感じ」"
    },
    {
        "name": "恭介",
        "message": "「いや、その、後ろの方なんだけど」"
    },
    {
        "name": "明乃",
        "message": "「あっ・・・」"
    },
    {
        "name": "明乃",
        "message": "「・・・・・・」"
    },
    {
        "name": "明乃",
        "message": "「ちょっとひりひりするけど、もう平気」"
    },
    {
        "name": "恭介",
        "message": "「そっか・・・もしつらかったら貴賓室で痛み止めでも・・・」"
    },
    {
        "name": "明乃",
        "message": "「・・・・・・」"
    },
    {
        "message": "しまった。志乃さんのことを思い出させてしまったか。"
    },
    {
        "name": "恭介",
        "message": "「えっと・・・とにかくベタベタのままじゃ気持ち悪いだろ？」"
    },
    {
        "name": "明乃",
        "message": "「・・・・・・」"
    },
    {
        "name": "明乃",
        "message": "「うん、だからその・・・」"
    },
    {
        "name": "恭介",
        "message": "「なに・・・？」"
    },
    {
        "name": "明乃",
        "message": "「・・・・・・」"
    },
    {
        "name": "明乃",
        "message": "「体、拭きたいから・・・」"
    },
    {
        "name": "恭介",
        "message": "「・・・・・・」"
    },
    {
        "name": "恭介",
        "message": "「あっ・・・そうだよな、うん。じゃあ、廊下にいるから何かあったら呼んで」"
    },
    {
        "message": "明乃はコクリと頷く。俯いた顔に朱が差しているのは、くるむような熱気のせいだけではない。"
    },
    {
        "message": "俺はやたらと愛想笑いを浮かべながら、浴室から後退していった。"
    }
]