[
    {
        "message": "モニター越しに見た光景が脳裏に浮かぶ。便器に顔を押し込まれ、水を流される姿が。"
    },
    {
        "message": "三人の中でも特に可憐のやられようは酷かった。あの様子では一人きりにはしておけない。"
    },
    {
        "message": "俺は逃げていく可憐を追って階段を駆け上がった。"
    },
    {
        "name": "可憐",
        "message": "「ひっ！？　あ、うあ・・・！」"
    },
    {
        "message": "俺が追ってくることに気づくと、可憐はうろたえたように廊下を走りだした。"
    },
    {
        "message": "可憐の足取りはまだおぼつかない。だが、俺が追いつくよりもわずかに早く、モニタールームの中へ逃げ込む。"
    },
    {
        "message": "俺がドアに手を掛けると同時に、錠の下りる音がする。ノブを回してみるが扉はわずかも動かなかった。"
    },
    {
        "name": "可憐",
        "message": "「いや！！　こないで！！　私に近寄らないで！！」"
    },
    {
        "message": "叫び声が遠ざかっていく。ドアに鍵を掛けた上、部屋の端まで逃げたらしい。"
    },
    {
        "name": "可憐",
        "message": "「誰も！！　私のそばに来ないで！！　一人にしておいて！！　この部屋に入ってこないで！！」"
    },
    {
        "name": "可憐",
        "message": "「もういや！！　いやよ！！　こんなの、こんな・・・もう放っといて！！　私に近寄らないで！！　誰も！！」"
    },
    {
        "name": "恭介",
        "message": "「可憐・・・」"
    },
    {
        "name": "可憐",
        "message": "「私は、私は・・・！」"
    },
    {
        "name": "可憐",
        "message": "「いやよ・・・いや・・・誰も私の顔を見ないで・・・」"
    },
    {
        "message": "崩れるように、叫び声は嗚咽へと変わっていく。"
    },
    {
        "name": "可憐",
        "message": "「もういや・・・」"
    },
    {
        "name": "可憐",
        "message": "「こんなこと・・・いやよぉ・・・」"
    },
    {
        "message": "すすり泣きが萎んでいく。部屋の隅で膝を抱えているのか、可憐の声はひどく低い位置から聞こえた。"
    },
    {
        "message": "可憐のことは心配だが、これではどうすることもできない。"
    },
    {
        "message": "一人にしておくしかないのか・・・。"
    },
    {
        "message": "ドアにそっと手のひらを押しつける。金属の扉は冷え切っていて、可憐の頑なな拒絶を思わせた。"
    },
    {
        "name": "恭介",
        "message": "「可憐、お腹が空いたら降りてこいよ。何か作ってやるから」"
    },
    {
        "message": "目の前で閉ざされた扉にそう話しかけてから、俺はきびすを返した。"
    },
    {
        "message": "何歩も行かないうちに、部屋の中で人の動く気配がした。"
    },
    {
        "message": "素足の足音がドアに駆け寄る。直後、かすかに硬質な音が聞こえた。"
    },
    {
        "message": "鍵が開いた・・・？"
    },
    {
        "message": "俺は足を止め、モニタールームの入り口を振り返った。引き返すことはまだ躊躇われた。"
    },
    {
        "message": "金属の扉が壁から離れる。"
    },
    {
        "name": "可憐",
        "message": "「・・・ま、待って」"
    },
    {
        "message": "ほんのわずか開いたドアの隙間から、可憐の声が漏れてくる。それきり変化はない。"
    },
    {
        "message": "俺は少し迷ってからきびすを返し、可憐を怖がらせないようゆっくりとドアに近づいていく。"
    },
    {
        "name": "可憐",
        "message": "「ひっ・・・」"
    },
    {
        "message": "それでも可憐は扉の裏から逃げ出してしまった。ゆっくりとドアが閉まる。だが、鍵が掛けられた気配はなかった。"
    },
    {
        "message": "人の目に触れたくないためここまで逃げてきたのだが、一人になることへの恐怖心が今になってわいてきたのだろう。"
    },
    {
        "message": "俺は目の前にあるドアに手を掛けた。今度は抵抗もなく開かれる。"
    },
    {
        "name": "可憐",
        "message": "「っ・・・！」"
    },
    {
        "message": "モニタールームに入る。可憐はドアからつかず離れずといった位置に立っていた。ドアの開閉に思わず及び腰になるが、何とかその場に踏みとどまる。"
    },
    {
        "message": "予想していたのとは若干違っていた。可憐は睨むような顔つきを俺に見せていた。"
    },
    {
        "name": "可憐",
        "message": "「ち、違うんだからっ」"
    },
    {
        "message": "挑戦的な眼差しを投げかけながら、可憐は言い訳めいた言葉を口にする。"
    },
    {
        "message": "だが、何のことを言っているのかは俺にはわからなかった。聞き返す間もなく、可憐は訴えを続ける。"
    },
    {
        "name": "可憐",
        "message": "「違う、そうじゃないの。恭介、勘違いしてる。あたし、ひどいことなんてされてないから」"
    },
    {
        "message": "ひきつった微笑み。俺はようやく全てを理解した。"
    },
    {
        "message": "可憐は知らない。俺がまさにこの部屋でその光景を見ていたことを。だから・・・。"
    },
    {
        "message": "いや、可憐自身がそう信じ込もうとしているのかもしれない。自分の身に何も起きていないと。"
    },
    {
        "name": "可憐",
        "message": "「うん、全然平気。恭介が心配するようなことは何もされてない。本当よ？　恭介の誤解なんだから」"
    },
    {
        "name": "可憐",
        "message": "「ただ服は持って行かれちゃったけどね。でもそれだけ。襲われてもいないの。あいつと出くわしてもいないし」"
    },
    {
        "name": "可憐",
        "message": "「私が逃げ出したから勘違いしたのよね、恭介は。だってこんな格好だもん。なのに恭介ったら追いかけてきたりして」"
    },
    {
        "name": "可憐",
        "message": "「だから誤解しないでよね。呼び止めたのもその辺りをはっきりさせたかったから。変に気を回されるのも困るし。だって何もされてないんだから」"
    },
    {
        "message": "可憐・・・。"
    },
    {
        "name": "可憐",
        "message": "「何もされてない何もされてない・・・そうよ、何もされてないんだから。私は何もされてない。何もされてないのよ」"
    },
    {
        "name": "恭介",
        "message": "「ああ・・・そうだったのか」"
    },
    {
        "message": "これ以上は聞くに堪えない。焼けた鉄を吐きだす思いで、俺はようやくそれだけを口にする。"
    },
    {
        "message": "可憐は俺のことを見つめ、不意に表情を険しくする。"
    },
    {
        "name": "可憐",
        "message": "「・・・うそ、信じてない」"
    },
    {
        "name": "可憐",
        "message": "「どうして・・・私の言うことを信じてくれないの？」"
    },
    {
        "name": "恭介",
        "message": "「いや、疑ってなんか」"
    },
    {
        "name": "可憐",
        "message": "「嘘よ！！　どうして疑うの！？　いやあっ！！！　そんな、そんな憐れんだ目で見ないで！！！」"
    },
    {
        "name": "可憐",
        "message": "「私のこと、そんな・・・やめてやめてやめて！！！　違うって言ってるでしょ！！！　何もなかったって！！！」"
    },
    {
        "message": "可憐の態度が豹変し、ヒステリックに喚き散らす。もう誰の言葉も聞きたくないとばかりに耳を塞ぎ、髪を振り乱して頭を振る。"
    },
    {
        "name": "恭介",
        "message": "「可憐！！」"
    },
    {
        "message": "可憐の動きが不意に止まる。俺の呼びかけが届いたわけではなく、可憐は俺のことをまともに見ていない。"
    },
    {
        "name": "可憐",
        "message": "「・・・そうよ。そんなに<R疑る|うたぐる>んだったら確かめればいいじゃない」"
    },
    {
        "name": "可憐",
        "message": "「確かめればいいでしょ、私の体がどうなってるか。ねえ、そうしてよ」"
    },
    {
        "message": "可憐は卑屈な笑みを浮かべると、自分のショーツへ手を掛ける。"
    },
    {
        "message": "俺は思わず目を逸らした。するすると下着の降ろされる音が聞こえてくる。"
    },
    {
        "name": "可憐",
        "message": "「ほら、見て。ちゃんと見てよ。私のここ、どうもなってないでしょ？」"
    },
    {
        "name": "恭介",
        "message": "「・・・やめてくれ・・・・・・」"
    },
    {
        "name": "可憐",
        "message": "「どうして確かめないの？　ああ、この格好じゃよく見えないよね。だったら・・・」"
    },
    {
        "message": "はしたなく足を開く気配。俺は顔を戻しかけ、慌てて目をきつく閉じる。"
    },
    {
        "name": "可憐",
        "message": "「ほら、これならいいでしょ？　もっと近づいてちゃんと調べてよ。綺麗なものでしょ？　ひどいことされた跡なんてある？」"
    },
    {
        "name": "可憐",
        "message": "「よく見て、前も後ろも変なとこなんてないから。傷もついてないし血も出てないわよ」"
    },
    {
        "name": "可憐",
        "message": "「何なら中まで広げて見せようか？　膜を確かめる？　ん、んんっ・・・これでどう？　奥まで見えるでしょ？」"
    },
    {
        "name": "可憐",
        "message": "「周りにこびりついてるヒダみたいなものがそうよ。ふふ・・・封がしてあると思った？　真ん中が開いてるのは元からそうなの」"
    },
    {
        "name": "可憐",
        "message": "「どうしたの恭介？　もっと近づいて確かめなさいよ。私が何でもないってことを」"
    },
    {
        "name": "可憐",
        "message": "「調べないの？　だったら疑いも晴れたってことだよね？　みんなにも恭介の口からちゃんと・・・」"
    },
    {
        "message": "こぷ・・・。"
    },
    {
        "name": "可憐",
        "message": "「あ・・・」"
    },
    {
        "message": "可憐の股間から、綺麗なピンク色をした割れ目から、白濁した粘液が一筋垂れてくる。"
    },
    {
        "message": "信じられない信じられない。可憐は目を見開く。"
    },
    {
        "name": "可憐",
        "message": "「ち、ちが・・・こんなこと・・・やだ、ちがう・・・」"
    },
    {
        "name": "可憐",
        "message": "「うそ、うそよこんなの・・・あ、恭介、これはちがうの、だから・・・」"
    },
    {
        "message": "ひきつりながら笑う可憐の瞳に、透明な液体が盛り上がってくる。それは可憐の頬を伝い落ちて涙となった。"
    },
    {
        "name": "可憐",
        "message": "「あ・・・あ・・・うぁ・・・」"
    },
    {
        "message": "可憐の顔がみるみる崩れていく。"
    },
    {
        "name": "可憐",
        "message": "「う・・・ううっ・・・」"
    },
    {
        "name": "可憐",
        "message": "<S9>「あああいやああああああっっっ！！？？」<S5>"
    },
    {
        "name": "可憐",
        "message": "<S9>「ちがうちがうちがう！！！　こんな、こんなのうそよおおおお！！！」<S5>"
    },
    {
        "name": "恭介",
        "message": "「可憐・・・」"
    },
    {
        "name": "可憐",
        "message": "<S9>「いやいやいやあああっっ！！！　ちがうちがう！！！　こんなの私じゃない！！！　私の体じゃないっっっ！！！」<S5>"
    },
    {
        "name": "可憐",
        "message": "<S9>「いやああっ！！　いやよおおっ！！　助けて、こんなのいやあああっっ！！！」<S5>"
    },
    {
        "name": "可憐",
        "message": "<S9>「いやいや！！　私じゃない私じゃない！！　こんなのちがう！！　誰か助けてっっ！！！　ここから出してえええっ！！」<S5>"
    },
    {
        "name": "恭介",
        "message": "「可憐・・・！」"
    },
    {
        "message": "錯乱する可憐。その手首を俺は思わずつかんでしまう。"
    },
    {
        "name": "可憐",
        "message": "<S9>「やだああああっっっ！！！　帰る、帰るのおおお！！！　もうこんなのいやあああっ！！！　おうちに帰してえええっ！！！」<S5>"
    },
    {
        "message": "可憐は俺の手を振り払うように暴れだし、でたらめに拳を振り上げる。その一発が俺の頬を打つ。"
    },
    {
        "message": "続いて二発三発。やがて可憐は両手で俺の肩や胸をめちゃくちゃに叩き始める。"
    },
    {
        "message": "だが、さして痛みはない。武道の心得がある者の拳とは思えなかった。"
    },
    {
        "message": "気の済むまで叩くにまかせながら、俺は可憐の肩を抱き寄せた。"
    },
    {
        "message": "羽をばたつかせる小鳥がどこかへ飛び出さないように。"
    },
    {
        "message": "やがて殴る力も衰え、可憐は俺の腕の中で崩れ落ちる。"
    },
    {
        "name": "可憐",
        "message": "「あああああっ・・・！！　うああああっ・・・！！」"
    },
    {
        "message": "後は、可憐は年端もいかない少女のように声を上げてただ泣きじゃくる。"
    },
    {
        "message": "それも尽きると、可憐は鼻をすすり上げながらおとなしくなった。"
    },
    {
        "message": "泣き疲れ、俺に体重を預けてくる可憐。彼女の体は思っていたよりもずっとか細かった。"
    },
    {
        "message": "俺は最小限の動きで自分の身からシャツを抜き取った。"
    },
    {
        "message": "なおも震える可憐の肩に、真っ白なシャツがふわりと舞い降りる。"
    },
    {
        "name": "可憐",
        "message": "「っ・・・」"
    },
    {
        "message": "もそもそ。"
    },
    {
        "message": "眠っているとばかり思っていた可憐が身じろぎをする。顔を伏せたまま、ゆっくりと押し返すように俺から身を離す。"
    },
    {
        "message": "それきり、可憐は表情を隠すようにあちらを向く。肩に掛けられたシャツを握りしめてぎゅっと胸元を合わせる。"
    },
    {
        "message": "二人の間にはまだ沈黙が横たわっていたが、可憐がすでに正気を取り戻したことは察せられる。"
    },
    {
        "message": "赤く染まった首筋が、そのことを言葉よりも確かに語っていた。"
    },
    {
        "message": "湿った空気は、にわかには晴れなかった。"
    },
    {
        "message": "抱き合っていたことよりも、感情をむき出しにしてしまったことが可憐にとっては気恥ずかしいようだ。"
    },
    {
        "message": "だが、先に沈黙を破ったのは可憐だった。"
    },
    {
        "name": "可憐",
        "message": "「・・・そろそろ戻らないと」"
    },
    {
        "message": "不自然なくらい首をねじ曲げ、決して俺の方は見ようとしない。まるで向こう隣にいる誰かに話しかけているようだった。"
    },
    {
        "message": "俺も抱き寄せた手前、極力可憐のことは直視せずに立ち上がる。"
    },
    {
        "message": "だが、言い出したはずの可憐がいっこうに腰を上げようとしない。"
    },
    {
        "name": "可憐",
        "message": "「だから、一緒に戻ったら変な誤解されるからっ」"
    },
    {
        "message": "訝しむ気配を察したのか、可憐はそう言いながらモニタールームの出口を指さす。"
    },
    {
        "message": "可憐はまだ俺からそっぽを向いていた。泣き腫らした目を見られたくないというのは、いつもの調子が戻ってきたという証拠でもあるだろう。"
    },
    {
        "message": "もう一人にしても大丈夫そうだ。俺は可憐を残してモニタールームを後にする。"
    },
    {
        "name": "可憐",
        "message": "「ま、待って」"
    },
    {
        "message": "少し慌てた様子で呼び止める声に、俺は振り返らず答える。"
    },
    {
        "name": "恭介",
        "message": "「わかってる、余計なことは言わない」"
    },
    {
        "name": "可憐",
        "message": "「そうじゃなくて、その・・・ありがとぅ」"
    },
    {
        "message": "つまりながらの感謝の言葉は、後へ行くほど弱々しくかすれていく。"
    },
    {
        "message": "俺は振り向かず肩越しに指を二本揃えてみせる。恩を高く売りつけるのは柄じゃない。"
    },
    {
        "name": "恭介",
        "message": "「今度膝枕してやるよ」"
    },
    {
        "name": "可憐",
        "message": "「ばかっ！」"
    },
    {
        "message": "飛んできたバケツを、後ろ手に閉めたドアで受け止める。"
    },
    {
        "message": "モニタールームを後にしてから、俺はまっすぐグリルへやって来た。"
    },
    {
        "message": "すでに物音は聞こえない。厨房を覗き込んでみるが、恵がいる気配はなかった。"
    },
    {
        "message": "荒れて金物に当たっただけならいいのだが・・・まあ、取り越し苦労の可能性だってある。ただ積んであった鍋釜が崩れたのかもしれない。"
    },
    {
        "message": "そう自分に説明しながら、俺は船首へ向かった。"
    }
]