[
    {
        "name": "恭介",
        "message": "「まあ、よくあるパターンとしては本人の生年月日というのがあるな」"
    },
    {
        "name": "明乃",
        "message": "「・・・・・・」"
    },
    {
        "name": "恭介",
        "message": "「ちょっと待て、なぜそこでお前が黙り込む？」"
    },
    {
        "message": "明乃はバツが悪そうな顔で露骨に俺から目をそらす。"
    },
    {
        "name": "恭介",
        "message": "「母親の誕生日くらい憶えてるよな？」"
    },
    {
        "name": "明乃",
        "message": "「あたしは２月１４日」"
    },
    {
        "name": "恭介",
        "message": "「お前のことは聞いてない」"
    },
    {
        "name": "明乃",
        "message": "「忘れちゃってたの・・・？　あたしの誕生日・・・」"
    },
    {
        "name": "恭介",
        "message": "「憶えてる憶えてる。つか忘れようにも忘れるか。いつもバレンタインと一緒にされるって泣くからわざわざ日を変えて二度も・・・って何を言わせる」"
    },
    {
        "message": "俺は両手で明乃の顔を挟んでブーにする。"
    },
    {
        "name": "恭介",
        "message": "「ぶっちゃけ忘れたんだろ、ああ？」"
    },
    {
        "name": "明乃",
        "message": "「むぎゅ・・・さっきまでは憶えてたもん」"
    },
    {
        "name": "恭介",
        "message": "「まだ言うか」"
    },
    {
        "name": "明乃",
        "message": "「だって改めて聞くから！　その拍子に忘れちゃったの！」"
    },
    {
        "name": "恭介",
        "message": "「まったく、仕方ないな・・・」"
    },
    {
        "message": "これ以上、明乃の顔であんなことやこんなことをしても志乃さんの誕生日が出てくるわけもない。"
    },
    {
        "message": "他の番号を考えてみるか。"
    },
    {
        "name": "恭介",
        "message": "「・・・待てよ、生年月日だったらメーラーの中にないか？」"
    },
    {
        "message": "志乃さんは専門外のことには極端に疎いから、ウィザードに促されるまま個人データを登録しているかもしれない。"
    },
    {
        "message": "俺たちは貴賓室の重厚な作りとは不釣り合いなＯＡデスクに取りつき、ノートＰＣの電源を入れた。"
    },
    {
        "message": "かすかなモーター音に続いて液晶画面が明かりが投じられる。"
    },
    {
        "message": "ＯＳのロゴが表示され、そこからがいささか長かったがようやく起動画面が表示される。認証画面はＥＮＴＥＲキー連打ですっとばす。"
    },
    {
        "name": "恭介",
        "message": "「っ・・・くそ！」"
    },
    {
        "message": "慌てすぎてエラーが出たか。俺はメッセージを閉じ、改めて認証画面でＯＫボタンをクリックする。"
    },
    {
        "name": "恭介",
        "message": "「パスが設定されてやがるのか！」"
    },
    {
        "name": "明乃",
        "message": "「恭ちゃん、またダメだっていってるよ！」"
    },
    {
        "name": "恭介",
        "message": "「ええい、わかってるわい！　金庫のナンバーの前にＰＣのパスか、これじゃきりがな・・・ちょっと待てよ」"
    },
    {
        "message": "もしやと思い立ち、ユーザー名を管理者に書き直しパスなしで入り直してみる。"
    },
    {
        "message": "今度はエラーメッセージが出ることもなく、デフォルトの起動音が鳴り響き風景画の壁紙が表示される。"
    },
    {
        "name": "恭介",
        "message": "「管理者権限だとフリーパス・・・やっぱり志乃さんだ・・・」"
    },
    {
        "message": "事件が終わったらちゃんと教えてやらないと。"
    },
    {
        "message": "まだＨＤＤがカリカリいっている間にメーラーの起動をキューに叩き込む。"
    },
    {
        "message": "メーラーはＯＳに標準装備のもので機能の配置は見慣れたものだった。迷うことなくアドレス帳を表示する。"
    },
    {
        "message": "あっ・・・。"
    },
    {
        "message": "仕事、家族、私的交友関係が無秩序に並ぶ中、見慣れたメアドが目に飛び込んでくる。そういえば一度メールのやり取りをしたっけか。"
    },
    {
        "name": "明乃",
        "message": "「あれ・・・？」"
    },
    {
        "message": "すぐさま志乃さんのアカウントを開いてアドレス帳を下敷きにする。"
    },
    {
        "name": "明乃",
        "message": "「今の・・・」"
    },
    {
        "name": "恭介",
        "message": "「アンテナがやられてるから今はメールの送受信はできないぞ」"
    },
    {
        "message": "何食わぬ顔で作業を続け、アカウントの個人データを表示する。"
    },
    {
        "name": "恭介",
        "message": "「・・・・・・」"
    },
    {
        "name": "明乃",
        "message": "「・・・・・・」"
    },
    {
        "message": "月と日にちはいいとして、生まれ年は明らかに無理があった。だいたいこれだと明乃はいったい幾つなんだ？"
    },
    {
        "message": "こんなところまで志乃さん・・・女心だな・・・。"
    },
    {
        "message": "しかし金庫の番号に設定するとしたら事実よりもこちらの生年月日の方だろう。"
    },
    {
        "message": "偽りと察しながら、俺はメーラーに書かれた数字で金庫の解錠を試みる。"
    },
    {
        "message": "だが扉は固く閉ざされたままだった。"
    }
]