[
    {
        "message": "その直前、俺は長剣をひと振りした。"
    },
    {
        "message": "岸田は声もあげずに暗い海へ落ちていく。"
    },
    {
        "message": "甲板には奴の指が散らばっていた。"
    },
    {
        "message": "それが精いっぱいだった。直接殺すことはできなかった。"
    },
    {
        "message": "だが、結果は同じことだ。ここで海に落ちて助かる確率はゼロに等しい。"
    },
    {
        "message": "じきに恵も甲板に出てくる。"
    },
    {
        "name": "恵",
        "message": "「殺したの・・・？」"
    },
    {
        "message": "図書室から状況が見えていたのか、恵は手すりから海面を覗き見る。"
    },
    {
        "message": "そこにはもはや岸田の存在はかけらも見あたらなかった。"
    },
    {
        "name": "恭介",
        "message": "「ああ」"
    },
    {
        "message": "何もかも終わった。\\nやっと・・・。"
    },
    {
        "message": "これまでの反動で一気に力が抜ける。手から離れた長剣が甲板でからりと音を立てた。"
    },
    {
        "name": "恵",
        "message": "「・・・死んだのね」"
    },
    {
        "message": "恵は甲板に散らばった指を見下ろし、そう呟いた。"
    },
    {
        "name": "恭介",
        "message": "「・・・ああ」"
    },
    {
        "name": "恵",
        "message": "「そう・・・」"
    },
    {
        "message": "呪いのように、恵にまとわりついていた巨悪は消えた。"
    },
    {
        "message": "それについて、恵の反応は意外と淡泊なものだった。"
    },
    {
        "message": "だが、やがて恵の体はぶるぶると震えだす。"
    }
]